HEALTH_MANAGEMENT.py
Health_management-0.1.dist-info/LICENSE.txt
Health_management-0.1.dist-info/METADATA
Health_management-0.1.dist-info/WHEEL
Health_management-0.1.dist-info/top_level.txt
Health_management-0.1.dist-info/RECORD
