Metadata-Version: 2.1
Name: Health-management
Version: 0.1
Summary: This is a package in which you can manage you health by making a simple program
Home-page: https://github.com/Anshu370/Health_management_system
Author: Anshu Gupta
License: UNKNOWN
Keywords: health management python,health management system,python health management,health management
Platform: UNKNOWN
Classifier: Programming Language :: Python :: 3
Classifier: License :: OSI Approved :: MIT License
Classifier: Operating System :: OS Independent
Requires-Python: >=3.9
Requires-Dist: datetime
